examples/__init__.py
examples/pp_rdf.py
examples/pp_tv.py
examples/write_tv.py
spdx/__init__.py
spdx/annotation.py
spdx/checksum.py
spdx/config.py
spdx/creationinfo.py
spdx/document.py
spdx/exceptions.json
spdx/file.py
spdx/licenses.json
spdx/package.py
spdx/relationship.py
spdx/review.py
spdx/snippet.py
spdx/tv_to_rdf.py
spdx/utils.py
spdx/version.py
spdx/cli_tools/__init__.py
spdx/cli_tools/convertor.py
spdx/cli_tools/parser.py
spdx/parsers/__init__.py
spdx/parsers/builderexceptions.py
spdx/parsers/jsonparser.py
spdx/parsers/jsonyamlxml.py
spdx/parsers/jsonyamlxmlbuilders.py
spdx/parsers/loggers.py
spdx/parsers/parse_anything.py
spdx/parsers/rdf.py
spdx/parsers/rdfbuilders.py
spdx/parsers/tagvalue.py
spdx/parsers/tagvaluebuilders.py
spdx/parsers/validations.py
spdx/parsers/xmlparser.py
spdx/parsers/yamlparser.py
spdx/parsers/lexers/__init__.py
spdx/parsers/lexers/tagvalue.py
spdx/writers/__init__.py
spdx/writers/json.py
spdx/writers/jsonyamlxml.py
spdx/writers/rdf.py
spdx/writers/tagvalue.py
spdx/writers/write_anything.py
spdx/writers/xml.py
spdx/writers/yaml.py
ws_spdx_tools-0.7.0a4.post6.dist-info/LICENSE
ws_spdx_tools-0.7.0a4.post6.dist-info/METADATA
ws_spdx_tools-0.7.0a4.post6.dist-info/WHEEL
ws_spdx_tools-0.7.0a4.post6.dist-info/entry_points.txt
ws_spdx_tools-0.7.0a4.post6.dist-info/top_level.txt
ws_spdx_tools-0.7.0a4.post6.dist-info/RECORD
