Metadata-Version: 2.1
Name: ws-spdx-tools
Version: 0.7.0a4.post6
Summary: SPDX parser and tools.
Home-page: https://github.com/spdx/tools-python
Author: Ahmed H. Ismail
Author-email: ahm3d.hisham@gmail.com
Maintainer: Philippe Ombredanne, SPDX group at the Linux Foundation and others
Maintainer-email: pombredanne@gmail.com
License: Apache-2.0
Platform: UNKNOWN
Classifier: Intended Audience :: Developers
Classifier: License :: OSI Approved :: Apache Software License
Classifier: Programming Language :: Python :: 3.6
Classifier: Programming Language :: Python :: 3.7
Classifier: Programming Language :: Python :: 3.8
Classifier: Programming Language :: Python :: 3.9
Requires-Python: >=3.6
License-File: LICENSE
Requires-Dist: ply
Requires-Dist: rdflib
Requires-Dist: click
Requires-Dist: pyyaml
Requires-Dist: xmltodict
